Metadata-Version: 1.0
Name: prob-dist-sd
Version: 0.1
Summary: Gaussian and Binomial distributions
Home-page: UNKNOWN
Author: Swastik Dashore
Author-email: swastik01tc@gmail.com
License: UNKNOWN
Platform: UNKNOWN
